run_protocol/__init__.py
run_protocol/main.py
run_protocol-0.1.0.dist-info/LICENSE
run_protocol-0.1.0.dist-info/METADATA
run_protocol-0.1.0.dist-info/WHEEL
run_protocol-0.1.0.dist-info/top_level.txt
run_protocol-0.1.0.dist-info/RECORD
