Metadata-Version: 2.2
Name: run_protocol
Version: 0.1.0
Summary: A Python library to control the Opentrons OT-2 and FLEX robot via HTTP API.
Home-page: https://github.com/yourusername/run_protocol
Author: Your Name
Author-email: your.email@example.com
Classifier: Programming Language :: Python :: 3
Classifier: License :: OSI Approved :: MIT License
Classifier: Operating System :: OS Independent
Requires-Python: >=3.7
License-File: LICENSE
Requires-Dist: requests
Dynamic: author
Dynamic: author-email
Dynamic: classifier
Dynamic: home-page
Dynamic: requires-dist
Dynamic: requires-python
Dynamic: summary
